jpaulorc_csv_converter/__init__.py
jpaulorc_csv_converter/converter.py
jpaulorc_csv_converter-0.1.3.dist-info/entry_points.txt
jpaulorc_csv_converter-0.1.3.dist-info/WHEEL
jpaulorc_csv_converter-0.1.3.dist-info/METADATA
jpaulorc_csv_converter-0.1.3.dist-info/RECORD
