Metadata-Version: 2.1
Name: jpaulorc-csv-converter
Version: 0.1.3
Summary: Convert csv to json and json to csv. Publishin only for leaning purposes.
Author: Joao Corte
Author-email: jpaulorc@gmail.com
Requires-Python: >=3.9,<4.0
Classifier: Programming Language :: Python :: 3
Classifier: Programming Language :: Python :: 3.10
Classifier: Programming Language :: Python :: 3.9
Requires-Dist: click (>=8.0.3,<9.0.0)
